Metadata-Version: 2.1
Name: XStatic-Moment-Timezone
Version: 0.5.22.0
Summary: Moment-Timezone 0.5.22 (XStatic packaging standard)
Home-page: https://github.com/moment/moment-timezone
Maintainer: Michal Arbet
Maintainer-email: michal.arbet@ultimum.io
License: (same as Moment-Timezone)
Keywords: moment_timezone xstatic
Platform: any
